make.py
sawsi/__init__.py
sawsi/api_doc/__init__.py
sawsi/api_doc/doc_generator.py
sawsi/aws/__init__.py
sawsi/aws/shared.py
sawsi/aws/apigateway/__init__.py
sawsi/aws/apigateway/api.py
sawsi/aws/codebuild/__init__.py
sawsi/aws/codebuild/api.py
sawsi/aws/codecommit/__init__.py
sawsi/aws/codecommit/api.py
sawsi/aws/cognito/__init__.py
sawsi/aws/cognito/api.py
sawsi/aws/dynamodb/__init__.py
sawsi/aws/dynamodb/api.py
sawsi/aws/dynamodb/config.py
sawsi/aws/dynamodb/util.py
sawsi/aws/dynamodb/wrapper.py
sawsi/aws/firehose/__init__.py
sawsi/aws/firehose/api.py
sawsi/aws/firehose/wrapper.py
sawsi/aws/iam/__init__.py
sawsi/aws/iam/wrapper.py
sawsi/aws/lambda_client/__init__.py
sawsi/aws/lambda_client/api.py
sawsi/aws/locking/__init__.py
sawsi/aws/locking/api.py
sawsi/aws/locking/wrapper.py
sawsi/aws/logs/__init__.py
sawsi/aws/logs/api.py
sawsi/aws/opensearch/__init__.py
sawsi/aws/opensearch/api.py
sawsi/aws/s3/__init__.py
sawsi/aws/s3/api.py
sawsi/aws/s3/wrapper.py
sawsi/aws/s3_db/__init__.py
sawsi/aws/s3_db/api.py
sawsi/aws/secrets_manager/__init__.py
sawsi/aws/secrets_manager/api.py
sawsi/aws/secrets_manager/wrapper.py
sawsi/aws/ses/__init__.py
sawsi/aws/ses/api.py
sawsi/aws/ses/wrapper.py
sawsi/aws/sms/__init__.py
sawsi/aws/sms/api.py
sawsi/aws/sms/wrapper.py
sawsi/aws/sns/__init__.py
sawsi/aws/sns/api.py
sawsi/aws/sns/wrapper.py
sawsi/aws/sqs/__init__.py
sawsi/aws/sqs/api.py
sawsi/aws/sqs/wrapper.py
sawsi/aws/ssm/__init__.py
sawsi/aws/ssm/api.py
sawsi/aws/ssm/wrapper.py
sawsi/handler/__init__.py
sawsi/handler/controller_decorator.py
sawsi/handler/router.py
sawsi/model/__init__.py
sawsi/model/base.py
sawsi/service/__init__.py
sawsi/service/searchengine.py
sawsi/shared/__init__.py
sawsi/shared/aws_es_proxy_util.py
sawsi/shared/class_util.py
sawsi/shared/dict_util.py
sawsi/shared/error_util.py
sawsi/shared/filter_exp_util.py
sawsi/shared/function_util.py
sawsi/shared/handler_util.py
sawsi/shared/hash_util.py
sawsi/shared/list_util.py
sawsi/shared/schedule_util.py
sawsi-19.90.dist-info/LICENSE
sawsi-19.90.dist-info/METADATA
sawsi-19.90.dist-info/WHEEL
sawsi-19.90.dist-info/entry_points.txt
sawsi-19.90.dist-info/top_level.txt
sawsi-19.90.dist-info/RECORD
