Metadata-Version: 2.1
Name: sawsi
Version: 19.90
License-File: LICENSE
Requires-Dist: requests==2.31.0
Requires-Dist: click~=8.1.7
